flet_blurhash/__init__.py
flet_blurhash/flet_blurhash.py
flutter/flet_blurhash/pubspec.lock
flutter/flet_blurhash/pubspec.yaml
flutter/flet_blurhash/lib/flet_blurhash.dart
flutter/flet_blurhash/lib/src/extension.dart
flutter/flet_blurhash/lib/src/flet_blurhash.dart
flet_blurhash-0.1.0.dist-info/METADATA
flet_blurhash-0.1.0.dist-info/WHEEL
flet_blurhash-0.1.0.dist-info/top_level.txt
flet_blurhash-0.1.0.dist-info/RECORD
