Metadata-Version: 2.4
Name: flet-blurhash
Version: 0.1.0
Summary: This library can make it easier for you if you want to display images smoothly.
Author-email: arief minardi <ariefminardi005@gmail.com>
Project-URL: Repository, https://github.com/arief05652/flet-blurhash
Project-URL: Issues, https://github.com/arief05652/flet-blurhash/issues
Requires-Python: >=3.12
Requires-Dist: flet>=0.80.0
